EpicEndpoints/EpicEndpoints.py
EpicEndpoints/__init__.py
EpicEndpoints/auth.py
EpicEndpoints-0.1.8.dist-info/LICENSE
EpicEndpoints-0.1.8.dist-info/METADATA
EpicEndpoints-0.1.8.dist-info/WHEEL
EpicEndpoints-0.1.8.dist-info/top_level.txt
EpicEndpoints-0.1.8.dist-info/RECORD
