Metadata-Version: 2.1
Name: EpicEndpoints
Version: 0.1.8
Summary: An easy way to access Epic Games' endpoints without clutter. 
Home-page: https://github.com/AtomicXYZ/EpicEndpoints
Author: AtomicXYZ
License: LICENSE
Project-URL: Documentation, https://github.com/AtomicXYZ/EpicEndpoints
Platform: UNKNOWN
License-File: LICENSE
Requires-Dist: requests
